torchei/__init__.py
torchei/fault_model.py
torchei/utils.py
torchei-1.0.0.dist-info/LICENSE
torchei-1.0.0.dist-info/METADATA
torchei-1.0.0.dist-info/WHEEL
torchei-1.0.0.dist-info/top_level.txt
torchei-1.0.0.dist-info/RECORD
