Metadata-Version: 2.1
Name: torchei
Version: 1.0.0
Summary: A toolbox about DNN Reliability
Home-page: https://github.com/TorchEI/TorchEI
Author-email: forcelesszheng@foxmail.com
License: UNKNOWN
Project-URL: Bug Tracker, https://github.com/TorchEI/TorchEI/issues
Keywords: pytorch,reliability,ErrorInjection,FaultInjection,BitFlip
Platform: UNKNOWN
Classifier: Programming Language :: Python :: 3
Classifier: License :: OSI Approved :: MIT License
Classifier: Operating System :: OS Independent
License-File: LICENSE
Requires-Dist: torch (>=1.8.0)
Requires-Dist: numpy (>=1.21.0)
Requires-Dist: torchstat
Requires-Dist: scipy
Requires-Dist: tqdm
Requires-Dist: torchvision
